zeus/__init__.py
zeus/conftest.py
zeus/changelog/__init__.py
zeus/changelog/arbitrary_version_pair_fetcher.py
zeus/changelog/consecutive_versions_fetcher.py
zeus/changelog/diff_utils.py
zeus/changelog/simple_changelog.py
zeus/changelog/util.py
zeus/changelog/graphql/__init__.py
zeus/changelog/graphql/util.py
zeus/changelog/graphql/types/__init__.py
zeus/changelog/graphql/types/changelog_entry.py
zeus/changelog/graphql/types/changelog_entry_field_entry.py
zeus/changelog/graphql/types/changelog_page.py
zeus/changelog/graphql/types/diff.py
zeus/changelog/graphql/types/version.py
zeus/changelog/graphql/types/version_comparison_entry.py
zeus/changelog/tests/__init__.py
zeus/changelog/tests/example_schema.py
zeus/changelog/tests/test_changelog.py
zeus/changelog/tests/test_simple_changelog.py
zeus/changelog/text/__init__.py
zeus/changelog/text/changelog_text.text.yaml
zeus/changelog/views/__init__.py
zeus/changelog/views/abstract_changelog_view.py
zeus/django/__init__.py
zeus/django/disconnect_signal.py
zeus/django/model_utils.py
zeus/django/must_be_logged_in_middleware.py
zeus/django/query_counting.py
zeus/django/test_must_be_logged_in_middleware.py
zeus/graphql/__init__.py
zeus/graphql/dataloader.py
zeus/graphql/graphiql_view_base.py
zeus/graphql/graphql_context.py
zeus/graphql/internal_query_executor_base.py
zeus/graphql/middleware.py
zeus/graphql/utils.py
zeus/graphql/testing/__init__.py
zeus/graphql/testing/fixtures.py
zeus/graphql/tests/__init__.py
zeus/graphql/tests/conftest.py
zeus/graphql/tests/test_dataloaders.py
zeus/graphql/types/__init__.py
zeus/graphql/types/has_non_serializable_record_mixin.py
zeus/graphql/types/version.py
zeus/i18n/__init__.py
zeus/i18n/text_entry_manager.py
zeus/i18n/text_maker.py
zeus/i18n/text_watcher.py
zeus/markdown/__init__.py
zeus/vanilla/__init__.py
zeus/vanilla/are_strings_close_enough.py
zeus/vanilla/flatten.py
zeus/vanilla/group_by.py
zeus/vanilla/is_ascii.py
zeus/versioning/__init__.py
zeus/versioning/core.py
titan_zeus-2.0.0.dist-info/METADATA
titan_zeus-2.0.0.dist-info/WHEEL
titan_zeus-2.0.0.dist-info/top_level.txt
titan_zeus-2.0.0.dist-info/RECORD
