Metadata-Version: 2.1
Name: titan-zeus
Version: 2.0.0
Home-page: https://github.com/TBS-EACPD/zeus
Author: AlexCLeduc
Classifier: Programming Language :: Python :: 3
Classifier: License :: OSI Approved :: MIT License
Classifier: Operating System :: OS Independent
